src/lib/__init__.py
src/lib/core/__init__.py
src/lib/core/config.py
src/lib/core/file_cache.py
src/lib/core/log.py
src/lib/core/template_engine.py
src/lib/package/__init__.py
athon/__init__.py
athon/agents.py
athon/chat.py
athon/rag.py
athon/system.py
src/lib/services/__init__.py
src/lib/services/agents/__init__.py
src/lib/services/agents/reasoning_engine.py
src/lib/services/agents/task_force.py
src/lib/services/agents/tool_repository.py
src/lib/services/agents/reasoning_engines/__init__.py
src/lib/services/agents/reasoning_engines/base.py
src/lib/services/agents/reasoning_engines/langchain/__init__.py
src/lib/services/agents/reasoning_engines/langchain/agent_executor.py
src/lib/services/agents/reasoning_engines/llamaindex/__init__.py
src/lib/services/agents/reasoning_engines/llamaindex/react.py
src/lib/services/agents/task_forces/__init__.py
src/lib/services/agents/task_forces/base.py
src/lib/services/agents/task_forces/crewai/__init__.py
src/lib/services/agents/task_forces/crewai/crew.py
src/lib/services/agents/task_forces/langgraph/__init__.py
src/lib/services/agents/task_forces/langgraph/state_graph.py
src/lib/services/agents/tool_repositories/__init__.py
src/lib/services/agents/tool_repositories/base.py
src/lib/services/agents/tool_repositories/langchain/__init__.py
src/lib/services/agents/tool_repositories/langchain/structured_tool.py
src/lib/services/chat/__init__.py
src/lib/services/chat/memory.py
src/lib/services/chat/message_manager.py
src/lib/services/chat/model.py
src/lib/services/chat/prompt_render.py
src/lib/services/chat/memories/__init__.py
src/lib/services/chat/memories/base.py
src/lib/services/chat/memories/langchain/__init__.py
src/lib/services/chat/memories/langchain/buffer.py
src/lib/services/chat/memories/langchain/buffer_window.py
src/lib/services/chat/memories/langchain/chroma_store_retriever.py
src/lib/services/chat/memories/langchain/custom_remote.py
src/lib/services/chat/memories/langchain/summary.py
agentic_python-0.2.0.dist-info/METADATA
agentic_python-0.2.0.dist-info/WHEEL
agentic_python-0.2.0.dist-info/licenses/LICENCE.md
agentic_python-0.2.0.dist-info/RECORD
