Metadata-Version: 2.4
Name: agentic-python
Version: 0.2.0
Summary: Athon is the agentic-python library to create the HPE Agentic Tool Mesh platform services. This is an innovative platform designed to streamline and enhance the use of AI in various applications. It serves as a central hub to orchestrate 'Intelligent Plugins,' optimizing AI interactions and processes.
Project-URL: Homepage, https://github.com/HewlettPackard/llmesh/wiki
Project-URL: Repository, https://github.com/HewlettPackard/llmesh
Author-email: Antonio Fin <antonio.fin@hpe.com>
License-Expression: MIT
License-File: LICENCE.md
Keywords: Athon,HPE,LLM Agentic Tool Mesh,LLM Agentic Tool Platform
Classifier: Development Status :: 4 - Beta
Classifier: Intended Audience :: Developers
Classifier: License :: OSI Approved :: MIT License
Classifier: Programming Language :: Python :: 3
Requires-Python: <3.13,>=3.11
Requires-Dist: flask<4,>=3.0.3
Requires-Dist: jinja2<4,>=3.1.4
Requires-Dist: langchain<0.4,>=0.3.4
Requires-Dist: pydantic<3,>=2.9.2
Requires-Dist: pyopenssl<25,>=24.2.1
Requires-Dist: python-certifi-win32<2,>=1.6.1; sys_platform == 'win32'
Requires-Dist: python-multipart<0.0.21,>=0.0.18
Requires-Dist: pyyaml<7,>=6.0.2
Provides-Extra: agents
Requires-Dist: crewai[tools]<0.90.0,>0.80.0; extra == 'agents'
Requires-Dist: langchain-anthropic<0.3,>=0.2.3; extra == 'agents'
Requires-Dist: langchain-community<0.4,>=0.3.3; extra == 'agents'
Requires-Dist: langchain-google-genai<3,>=2.0.1; extra == 'agents'
Requires-Dist: langchain-mistralai<0.3,>=0.2.0; extra == 'agents'
Requires-Dist: langchain-nvidia-ai-endpoints<0.4,>=0.3.0; extra == 'agents'
Requires-Dist: langchain-openai<0.3,>=0.2.3; extra == 'agents'
Requires-Dist: langgraph<0.3,>=0.2.39; extra == 'agents'
Requires-Dist: llama-index-llms-openai<0.4,>=0.3; extra == 'agents'
Requires-Dist: llama-index<0.13,>=0.12.3; extra == 'agents'
Requires-Dist: vllm>=0.8; extra == 'agents'
Provides-Extra: all
Requires-Dist: chromadb<0.6.00,>0.4.24; extra == 'all'
Requires-Dist: crewai[tools]<0.90.0,>0.80.0; extra == 'all'
Requires-Dist: langchain-anthropic<0.3,>=0.2.3; extra == 'all'
Requires-Dist: langchain-community<0.4,>=0.3.3; extra == 'all'
Requires-Dist: langchain-google-genai<3,>=2.0.1; extra == 'all'
Requires-Dist: langchain-mistralai<0.3,>=0.2.0; extra == 'all'
Requires-Dist: langchain-nvidia-ai-endpoints<0.4,>=0.3.0; extra == 'all'
Requires-Dist: langchain-openai<0.3,>=0.2.3; extra == 'all'
Requires-Dist: langgraph<0.3,>=0.2.39; extra == 'all'
Requires-Dist: llama-index-llms-openai<0.4,>=0.3; extra == 'all'
Requires-Dist: llama-index<0.13,>=0.12.3; extra == 'all'
Requires-Dist: markitdown<0.1.0,>=0.0.1a3; extra == 'all'
Requires-Dist: matplotlib<4,>=3.9.2; extra == 'all'
Requires-Dist: openpyxl<4,>=3.1.5; extra == 'all'
Requires-Dist: pymilvus[model]<3,>=2.5.3; extra == 'all'
Requires-Dist: pymupdf<2,>=1.24.11; extra == 'all'
Requires-Dist: qdrant-client<1.13.0,>1.12.0; extra == 'all'
Requires-Dist: sentence-transformers<3.4.0,>3.2.0; extra == 'all'
Requires-Dist: torch<2.7.0,>=2.6.0; extra == 'all'
Requires-Dist: transformers>=4.48.0; extra == 'all'
Requires-Dist: umap-learn<0.6,>=0.5.7; extra == 'all'
Requires-Dist: umap<0.2,>=0.1.1; extra == 'all'
Requires-Dist: unstructured[docx,pdf,pptx,xlsx]<0.17,>=0.16.0; extra == 'all'
Requires-Dist: vllm>=0.8; extra == 'all'
Provides-Extra: chat
Requires-Dist: langchain-anthropic<0.3,>=0.2.3; extra == 'chat'
Requires-Dist: langchain-community<0.4,>=0.3.3; extra == 'chat'
Requires-Dist: langchain-google-genai<3,>=2.0.1; extra == 'chat'
Requires-Dist: langchain-mistralai<0.3,>=0.2.0; extra == 'chat'
Requires-Dist: langchain-nvidia-ai-endpoints<0.4,>=0.3.0; extra == 'chat'
Requires-Dist: langchain-openai<0.3,>=0.2.3; extra == 'chat'
Requires-Dist: llama-index-llms-openai<0.4,>=0.3; extra == 'chat'
Requires-Dist: llama-index<0.13,>=0.12.3; extra == 'chat'
Requires-Dist: vllm>=0.8; extra == 'chat'
Provides-Extra: rag
Requires-Dist: chromadb<0.6.00,>0.4.24; extra == 'rag'
Requires-Dist: langchain-anthropic<0.3,>=0.2.3; extra == 'rag'
Requires-Dist: langchain-community<0.4,>=0.3.3; extra == 'rag'
Requires-Dist: langchain-google-genai<3,>=2.0.1; extra == 'rag'
Requires-Dist: langchain-mistralai<0.3,>=0.2.0; extra == 'rag'
Requires-Dist: langchain-nvidia-ai-endpoints<0.4,>=0.3.0; extra == 'rag'
Requires-Dist: langchain-openai<0.3,>=0.2.3; extra == 'rag'
Requires-Dist: llama-index-llms-openai<0.4,>=0.3; extra == 'rag'
Requires-Dist: llama-index<0.13,>=0.12.3; extra == 'rag'
Requires-Dist: markitdown<0.1.0,>=0.0.1a3; extra == 'rag'
Requires-Dist: matplotlib<4,>=3.9.2; extra == 'rag'
Requires-Dist: openpyxl<4,>=3.1.5; extra == 'rag'
Requires-Dist: pymilvus[model]<3,>=2.5.3; extra == 'rag'
Requires-Dist: pymupdf<2,>=1.24.11; extra == 'rag'
Requires-Dist: qdrant-client<1.13.0,>1.12.0; extra == 'rag'
Requires-Dist: sentence-transformers<3.4.0,>3.2.0; extra == 'rag'
Requires-Dist: torch<2.7.0,>=2.6.0; extra == 'rag'
Requires-Dist: transformers>=4.48.0; extra == 'rag'
Requires-Dist: umap-learn<0.6,>=0.5.7; extra == 'rag'
Requires-Dist: umap<0.2,>=0.1.1; extra == 'rag'
Requires-Dist: unstructured[docx,pdf,pptx,xlsx]<0.17,>=0.16.0; extra == 'rag'
Requires-Dist: vllm>=0.8; extra == 'rag'
Provides-Extra: test
Requires-Dist: pytest-optional-tests<0.2,>=0.1.1; extra == 'test'
Requires-Dist: pytest<9,>=8.3.3; extra == 'test'
